FlaskDaxingJiaocheng2017/README.md
FlaskDaxingJiaocheng2017/__init__.py
FlaskDaxingJiaocheng2017/__main__.py
FlaskDaxingJiaocheng2017/file.epub
FlaskDaxingJiaocheng2017/index.html
FlaskDaxingJiaocheng2017/css/__init__.py
FlaskDaxingJiaocheng2017/css/annotations.css
FlaskDaxingJiaocheng2017/css/main.css
FlaskDaxingJiaocheng2017/css/normalize.css
FlaskDaxingJiaocheng2017/css/popup.css
FlaskDaxingJiaocheng2017/font/__init__.py
FlaskDaxingJiaocheng2017/font/fontello.eot
FlaskDaxingJiaocheng2017/font/fontello.svg
FlaskDaxingJiaocheng2017/font/fontello.ttf
FlaskDaxingJiaocheng2017/font/fontello.woff
FlaskDaxingJiaocheng2017/img/__init__.py
FlaskDaxingJiaocheng2017/img/annotator-glyph-sprite.png
FlaskDaxingJiaocheng2017/img/annotator-icon-sprite.png
FlaskDaxingJiaocheng2017/img/apple-touch-icon.png
FlaskDaxingJiaocheng2017/img/cancelfullscreen.png
FlaskDaxingJiaocheng2017/img/close.png
FlaskDaxingJiaocheng2017/img/fullscreen.png
FlaskDaxingJiaocheng2017/img/loader.gif
FlaskDaxingJiaocheng2017/img/menu-icon.png
FlaskDaxingJiaocheng2017/img/save.png
FlaskDaxingJiaocheng2017/img/saved.png
FlaskDaxingJiaocheng2017/img/settings-s.png
FlaskDaxingJiaocheng2017/img/settings.png
FlaskDaxingJiaocheng2017/img/star.png
FlaskDaxingJiaocheng2017/js/__init__.py
FlaskDaxingJiaocheng2017/js/epub.js
FlaskDaxingJiaocheng2017/js/epub.min.js
FlaskDaxingJiaocheng2017/js/epub.min.map
FlaskDaxingJiaocheng2017/js/hooks.min.js
FlaskDaxingJiaocheng2017/js/hooks.min.map
FlaskDaxingJiaocheng2017/js/reader.js
FlaskDaxingJiaocheng2017/js/reader.js.map
FlaskDaxingJiaocheng2017/js/reader.min.js
FlaskDaxingJiaocheng2017/js/reader.min.map
FlaskDaxingJiaocheng2017/js/hooks/__init__.py
FlaskDaxingJiaocheng2017/js/hooks/extensions/__init__.py
FlaskDaxingJiaocheng2017/js/hooks/extensions/highlight.js
FlaskDaxingJiaocheng2017/js/libs/__init__.py
FlaskDaxingJiaocheng2017/js/libs/jquery.min.js
FlaskDaxingJiaocheng2017/js/libs/localforage.min.js
FlaskDaxingJiaocheng2017/js/libs/screenfull.js
flask_daxing_jiaocheng_2017-2024.3.3.0.dist-info/METADATA
flask_daxing_jiaocheng_2017-2024.3.3.0.dist-info/WHEEL
flask_daxing_jiaocheng_2017-2024.3.3.0.dist-info/entry_points.txt
flask_daxing_jiaocheng_2017-2024.3.3.0.dist-info/top_level.txt
flask_daxing_jiaocheng_2017-2024.3.3.0.dist-info/RECORD
